crackpy/__init__.py
crackpy/crack_detection/__init__.py
crackpy/crack_detection/correction.py
crackpy/crack_detection/detection.py
crackpy/crack_detection/line_intercept.py
crackpy/crack_detection/model.py
crackpy/crack_detection/data/__init__.py
crackpy/crack_detection/data/datapreparation.py
crackpy/crack_detection/data/dataset.py
crackpy/crack_detection/data/interpolation.py
crackpy/crack_detection/data/preprocess.py
crackpy/crack_detection/data/transforms.py
crackpy/crack_detection/deep_learning/__init__.py
crackpy/crack_detection/deep_learning/attention.py
crackpy/crack_detection/deep_learning/docu.py
crackpy/crack_detection/deep_learning/loss.py
crackpy/crack_detection/deep_learning/nets.py
crackpy/crack_detection/deep_learning/setup.py
crackpy/crack_detection/deep_learning/train.py
crackpy/crack_detection/pipeline/__init__.py
crackpy/crack_detection/pipeline/pipeline.py
crackpy/crack_detection/utils/__init__.py
crackpy/crack_detection/utils/basic.py
crackpy/crack_detection/utils/evaluate.py
crackpy/crack_detection/utils/plot.py
crackpy/crack_detection/utils/utilityfunctions.py
crackpy/fracture_analysis/__init__.py
crackpy/fracture_analysis/analysis.py
crackpy/fracture_analysis/crack_tip.py
crackpy/fracture_analysis/data_processing.py
crackpy/fracture_analysis/line_integration.py
crackpy/fracture_analysis/optimization.py
crackpy/fracture_analysis/pipeline.py
crackpy/fracture_analysis/plot.py
crackpy/fracture_analysis/read.py
crackpy/fracture_analysis/write.py
crackpy/structure_elements/__init__.py
crackpy/structure_elements/data_files.py
crackpy/structure_elements/material.py
crackpy/tests/__init__.py
crackpy/tests/test_crack_detection/__init__.py
crackpy/tests/test_crack_detection/test_data/__init__.py
crackpy/tests/test_crack_detection/test_data/test_datapreparation.py
crackpy/tests/test_crack_detection/test_data/test_dataset_and_transforms.py
crackpy/tests/test_crack_detection/test_data/test_interpolation.py
crackpy-1.2.3.dist-info/LICENSE
crackpy-1.2.3.dist-info/METADATA
crackpy-1.2.3.dist-info/WHEEL
crackpy-1.2.3.dist-info/top_level.txt
crackpy-1.2.3.dist-info/RECORD
